pylightxl/__init__.py
pylightxl/pylightxl.py
pylightxl-1.54.dist-info/LICENSE
pylightxl-1.54.dist-info/METADATA
pylightxl-1.54.dist-info/WHEEL
pylightxl-1.54.dist-info/top_level.txt
pylightxl-1.54.dist-info/RECORD
