Metadata-Version: 2.1
Name: pylightxl
Version: 1.54
Summary: A light weight excel read/writer for python27 and python3 with no dependencies
Home-page: https://github.com/PydPiper/pylightxl
Author: Viktor Kis
Author-email: realpydpiper@gmail.com
License: MIT
Platform: UNKNOWN
Classifier: Programming Language :: Python :: 2.7
Classifier: Programming Language :: Python :: 3
Classifier: Programming Language :: Python :: 3.6
Classifier: Programming Language :: Python :: 3.7
Classifier: Programming Language :: Python :: 3.8
Classifier: License :: OSI Approved :: MIT License
Classifier: Operating System :: OS Independent
Requires-Python: >=2.7
